pySHSpeex.cpython-37m-darwin.so
houndify/__init__.py
houndify/houndify.py
houndify/sample_stdin.py
houndify/sample_text.py
houndify/sample_wave.py
Houndify-2.0.2.dist-info/LICENSE.txt
Houndify-2.0.2.dist-info/METADATA
Houndify-2.0.2.dist-info/WHEEL
Houndify-2.0.2.dist-info/top_level.txt
Houndify-2.0.2.dist-info/RECORD
