Metadata-Version: 2.1
Name: Houndify
Version: 2.0.2
Summary: Houndify libraries and SoundHound speex encoder
Home-page: https://www.houndify.com/sdks#python
Author: Soundhound Inc.
Author-email: pypi-maintainer@soundhound.com
Maintainer: Soundhound Inc.
License: MIT
Keywords: houndify
Platform: UNKNOWN
Classifier: Programming Language :: Python :: 3
